Metadata-Version: 2.1
Name: ex-liangwangkuai
Version: 0.0.1
Summary: my first try
Home-page: http://github.com/
Author: linwk
Author-email: 2259214992@qq.com
Classifier: Programming Language :: Python :: 3
Classifier: Operating System :: OS Independent
